shellm/__init__.py
shellm/__main__.py
shellm/main.py
shellm-0.4.1.dist-info/LICENSE
shellm-0.4.1.dist-info/METADATA
shellm-0.4.1.dist-info/WHEEL
shellm-0.4.1.dist-info/entry_points.txt
shellm-0.4.1.dist-info/RECORD
