Metadata-Version: 2.1
Name: shellm
Version: 0.4.1
Summary: 
Author: Gabriel Altay
Author-email: gabriel.altay@gmail.com
Requires-Python: >=3.9
Classifier: Programming Language :: Python :: 3
Classifier: Programming Language :: Python :: 3.9
Classifier: Programming Language :: Python :: 3.10
Classifier: Programming Language :: Python :: 3.11
Requires-Dist: openai (>=0.28.0,<0.29.0)
Requires-Dist: pydantic (>=2.3.0,<3.0.0)
Requires-Dist: typer[all] (>=0.9.0,<0.10.0)
